automatheque/__init__.py
automatheque/factrice/__init__.py
automatheque/factrice/expedition.py
automatheque/factrice/preparation.py
automatheque/factrice/py.typed
automatheque/factrice/app/__init__.py
automatheque.factrice-0.10.1.dist-info/METADATA
automatheque.factrice-0.10.1.dist-info/WHEEL
automatheque.factrice-0.10.1.dist-info/entry_points.txt
automatheque.factrice-0.10.1.dist-info/top_level.txt
automatheque.factrice-0.10.1.dist-info/RECORD
