Metadata-Version: 2.1
Name: automatheque.factrice
Version: 0.10.1
Summary: Librairie et app simplifiée d'envoi de mail
Author-email: Marc <githubmarc@maj44.com>
License: GPLv3.0
Project-URL: Home, https://github.com/jaegerbobomb/automatheque
Project-URL: Repository, https://github.com/jaegerbobomb/automatheque.git
Requires-Python: >=3.8
Requires-Dist: automatheque >=0.9.6
Requires-Dist: automatheque.schema >=0.9.5
